scipper/__init__.py
scipper/Rigol/DS1000de.py
scipper/Rigol/__init__.py
scipper-0.1.6.dist-info/LICENSE
scipper-0.1.6.dist-info/METADATA
scipper-0.1.6.dist-info/WHEEL
scipper-0.1.6.dist-info/top_level.txt
scipper-0.1.6.dist-info/RECORD
